yunxiao/__init__.py
yunxiao/main.py
yunxiao/model/__init__.py
yunxiao/model/base.py
yunxiao/model/member.py
yunxiao/model/organization.py
yunxiao/model/project.py
yunxiao/model/status.py
yunxiao/model/workitem.py
yunxiao/model/workitemfield.py
yunxiao/model/workitemtype.py
yunxiao/sdk/__init__.py
yunxiao/sdk/base.py
yunxiao/sdk/category.py
yunxiao/sdk/condition.py
yunxiao/sdk/member_list.py
yunxiao/sdk/organization_list.py
yunxiao/sdk/project_detail.py
yunxiao/sdk/project_list.py
yunxiao/sdk/user_info.py
yunxiao/sdk/workflowstatus.py
yunxiao/sdk/workitem_detail.py
yunxiao/sdk/workitem_list.py
yunxiao/sdk/workitemfield.py
yunxiao/sdk/workitemtype.py
yunxiao/utils/__init__.py
yunxiao/utils/cache.py
yunxiao/utils/command.py
yunxiao/utils/config.py
yunxiao/utils/date.py
yunxiao/utils/output.py
yunxiao/utils/state.py
yunxiao/web/__init__.py
yunxiao/web/browser.py
yunxiao/web/cache.py
yunxiao/web/request.py
yunxiao_cli-0.1.0.dist-info/METADATA
yunxiao_cli-0.1.0.dist-info/WHEEL
yunxiao_cli-0.1.0.dist-info/entry_points.txt
yunxiao_cli-0.1.0.dist-info/top_level.txt
yunxiao_cli-0.1.0.dist-info/RECORD
