Metadata-Version: 2.2
Name: yunxiao-cli
Version: 0.1.0
Summary: A CLI tool for interacting with Alibaba Cloud Yunxiao
Home-page: https://github.com/python-cli/yunxiao-cli
Author: Wei Han
Author-email: xingheng.hax@qq.com
Classifier: Development Status :: 3 - Alpha
Classifier: Intended Audience :: Developers
Classifier: Topic :: Software Development :: Libraries :: Python Modules
Classifier: License :: OSI Approved :: MIT License
Classifier: Programming Language :: Python :: 3
Requires-Python: >=3.7
Requires-Dist: alibabacloud-tea
Requires-Dist: alibabacloud-tea-openapi
Requires-Dist: aliyun-python-sdk-core
Requires-Dist: aliyun-python-sdk-sts
Requires-Dist: aliyunsdkcore
Requires-Dist: click
Requires-Dist: PyYAML
Requires-Dist: requests
Requires-Dist: rich
Requires-Dist: selenium
Requires-Dist: webdriver-manager
Dynamic: author
Dynamic: author-email
Dynamic: classifier
Dynamic: description
Dynamic: description-content-type
Dynamic: home-page
Dynamic: requires-dist
Dynamic: requires-python
Dynamic: summary
